LICENSE.txt
MANIFEST.in
setup.py
anagram_solver/__init__.py
anagram_solver/__main__.py
anagram_solver/anagram_solver.py
anagram_solver/stuff.py
anagram_solver.egg-info/PKG-INFO
anagram_solver.egg-info/SOURCES.txt
anagram_solver.egg-info/dependency_links.txt
anagram_solver.egg-info/entry_points.txt
anagram_solver.egg-info/top_level.txt