Metadata-Version: 1.0
Name: anagram-solver
Version: 1.0.9
Summary: Solve anagrams with python
Home-page: https://github.com/patrickleweryharris/anagram-solver
Author: Patrick Lewery Harris
Author-email: patrick@plh.io
License: UNKNOWN
Platform: UNKNOWN
